{
  "mainMenu": [
    {
      "name": "Home",
      "link": "/"
    },
    {
      "name": "About",
      "link": "/about"
    },
    {
      "name": "Blog",
      "link": "/blog"
    },
    {
      "name": "Archive",
      "link": "/blog/archive"
    },
    {
      "name": "Categtories",
      "link": "/categories",
      "submenu": [
        {
          "name": "All",
          "link": "/categories"
        },
        {
          "name": "Tech",
          "link": "/categories/tech"
        },
        {
          "name": "Family",
          "link": "/categories/family"
        },
        {
          "name": "Anime",
          "link": "/categories/anime"
        },
        {
          "name": "Health + Fitness",
          "link": "/categories/health"
        }
      ]
    },
    {
      "name": "Tags",
      "link": "/tags",
      "submenu": [
        {
          "name": "Reviews",
          "link": "/tags/reviews"
        }, 
        {
          "name": "Thoughts",
          "link": "/tags/thoughts"
        }, 
        {
          "name": "fatherhood",
          "link": "/tags/fatherhood"
        }
      ]
    },
    {
      "name": "Contact",
      "link": "/contact"
    }
  ]
}